{
  "parent": "dinocustom:revival/illager_structure",
  "display": {
    "icon": {
      "item": "minecraft:chain_command_block",
      "nbt": "{CustomModelData:400012}"
    },
    "title": {
      "translate": "advancements.dnd.revival.chronomancer.title"
    },
    "description": {
      "translate": "advancements.dnd.revival.chronomancer.description"
    },
    "frame": "goal",
    "show_toast": true,
    "announce_to_chat": true,
    "hidden": false
  },
  "criteria": {
    "killed_ghast": {
      "trigger": "minecraft:impossible"
    }
  }
}
