{
  "name": "dnd:amber_mine/amber_spike",
  "fallback": "minecraft:empty",
  "elements": [{
    "weight": 10,
    "element": {
      "location": "dnd:amber_mine/caverns/amber/vertical_down_1block",
      "processors": "minecraft:empty",
      "projection": "rigid",
      "element_type": "minecraft:single_pool_element"
    }
  },
  {
    "weight": 5,
    "element": {
      "location": "dnd:amber_mine/caverns/amber/vertical_down_2block",
      "processors": "minecraft:empty",
      "projection": "rigid",
      "element_type": "minecraft:single_pool_element"
    }
  },
  {
    "weight": 10,
    "element": {
      "location": "dnd:amber_mine/caverns/amber/vertical_up_1block",
      "processors": "minecraft:empty",
      "projection": "rigid",
      "element_type": "minecraft:single_pool_element"
    }
  },
  {
    "weight": 5,
    "element": {
      "location": "dnd:amber_mine/caverns/amber/vertical_up_2block",
      "processors": "minecraft:empty",
      "projection": "rigid",
      "element_type": "minecraft:single_pool_element"
    }
  },
  {
    "weight": 1,
    "element": {
      "location": "dnd:amber_mine/caverns/amber/budding_up",
      "processors": "minecraft:empty",
      "projection": "rigid",
      "element_type": "minecraft:single_pool_element"
    }
  },
  {
    "weight": 1,
    "element": {
      "location": "dnd:amber_mine/caverns/amber/budding_down",
      "processors": "minecraft:empty",
      "projection": "rigid",
      "element_type": "minecraft:single_pool_element"
    }
  }]
}
